adaMVP/adj_mat_interactome.py
adaMVP/graph_builder.py
adaMVP/graphical_models.py
adaMVP/markov_model_dataframe.py
adaMVP/mvp_build_graph.py
adaMVP/sig_first_neighbors.py
adaMVP/study_bias.py
adaMVP/data/publications_all_genes.txt
adaMVP/data/unique_interactome_CanSAR_KEGG_Hi_union_012423.txt
adaMVP-1.0.1.dist-info/LICENSE.txt
adaMVP-1.0.1.dist-info/METADATA
adaMVP-1.0.1.dist-info/WHEEL
adaMVP-1.0.1.dist-info/top_level.txt
adaMVP-1.0.1.dist-info/RECORD
