Metadata-Version: 2.1
Name: adaMVP
Version: 1.0.1
Summary: Adaptive AI-Augmented Drug Discovery and Development Molecular Vulnerability Picker
Author-email: Ying Zhu <yzhu16@mdanderson.org>
Project-URL: Homepage, https://github.com/YingZ-A3D3a/A3D3a_MVP
Classifier: Programming Language :: Python :: 3
Classifier: License :: OSI Approved :: MIT License
Classifier: Operating System :: OS Independent
Requires-Python: >=3.7
License-File: LICENSE.txt
Requires-Dist: numpy >1.21
Requires-Dist: pandas >1.4
Requires-Dist: matplotlib >3.5
Requires-Dist: networkx >2.7
Requires-Dist: tqdm
